{"_ts":[1488577829,1488708566,1488751965],"_r":{"breakdown":{"html":{"bytes":[30217,30283,30300],"requests":[6,6,6]},"js":{"bytes":[350448,350343,350433],"requests":[18,18,18]},"css":{"bytes":[77427,77427,77426],"requests":[3,3,3]},"image":{"bytes":[349457,168716,140685],"requests":[13,13,13]},"flash":{"bytes":[0,0,0],"requests":[0,0,0]},"font":{"bytes":[98370,98428,98427],"requests":[5,5,5]},"other":{"bytes":[1867,1870,1866],"requests":[3,3,3]}},"date":[1488577829,1488708566,1488751965],"domElements":[426,426,425],"domInteractive":[2570,3228,2497],"firstPaint":[2433,3164,1988],"fullyLoaded":[4661,5329,4721],"id":["170303_BK_5T6T","170305_GZ_E7D","170305_PD_YJV"],"loadTime":[3401,4065,3491],"render":[3078,3574,2095],"SpeedIndex":[3226,3904,3346],"TTFB":[338,1068,364],"videoFrames":[[{"_t":0,"_vc":0},{"_t":3100,"_vc":58},{"_t":3400,"_vc":100}],[{"_t":0,"_vc":0},{"_t":3600,"_vc":4},{"_t":3900,"_vc":92},{"_t":4100,"_vc":100}],[{"_t":0,"_vc":0},{"_t":2100,"_vc":5},{"_t":3300,"_vc":47},{"_t":3500,"_vc":100}]],"visualComplete":[3400,4100,3500]}}