{"_ts":[1488577868,1488621633],"_r":{"breakdown":{"html":{"bytes":[14942,14940],"requests":[5,5]},"js":{"bytes":[334091,334237],"requests":[15,15]},"css":{"bytes":[76236,76265],"requests":[2,2]},"image":{"bytes":[29929,29958],"requests":[6,6]},"flash":{"bytes":[0,0],"requests":[0,0]},"font":{"bytes":[74423,74363],"requests":[4,4]},"other":{"bytes":[679,679],"requests":[1,1]}},"date":[1488577868,1488621633],"domElements":[669,669],"domInteractive":[2868,4802],"firstPaint":[2727,4592],"fullyLoaded":[4349,6213],"id":["170303_VZ_5T71","170304_SR_EFY"],"loadTime":[3558,5520],"render":[2786,4682],"SpeedIndex":[3136,5036],"TTFB":[718,2725],"videoFrames":[[{"_t":0,"_vc":0},{"_t":2800,"_vc":16},{"_t":3200,"_vc":100}],[{"_t":0,"_vc":0},{"_t":4700,"_vc":16},{"_t":5100,"_vc":100}]],"visualComplete":[3200,5100]}}